formularity/__init__.py
formularity/your_module.py
formularity_rfs-0.3.dist-info/LICENSE
formularity_rfs-0.3.dist-info/METADATA
formularity_rfs-0.3.dist-info/WHEEL
formularity_rfs-0.3.dist-info/entry_points.txt
formularity_rfs-0.3.dist-info/top_level.txt
formularity_rfs-0.3.dist-info/RECORD
