Metadata-Version: 2.1
Name: formularity-rfs
Version: 0.3
Summary: Пакет для оценки формульности фольклорных песен на русском языке
Home-page: https://github.com/valsidnenko/formularity_rfs
Author: Valeria Sidnenko
Author-email: valsidnenko@gmail.com
Classifier: Programming Language :: Python :: 3
Classifier: License :: OSI Approved :: MIT License
Classifier: Operating System :: OS Independent
Requires-Python: >=3.6
License-File: LICENSE
Requires-Dist: spacy
Requires-Dist: pymorphy2
Requires-Dist: numpy
Requires-Dist: scikit-learn
